{
  "no_wrap": true,
  "text_block_list": [
    {
      "name": "Maruzensky",
      "text": "No hay nada como estar en la pista de baile<n>con un traje de baño mientras\nagitas un abanico! ¡Este<n>es el placer de Burbulandia, chicas! ¡Wuuju!"
    },
    {
      "name": "Special Week",
      "text": "Así que <i>esta</i> es Burbulandia!"
    },
    {
      "name": "Monólogo"
    },
    {
      "name": "Monólogo",
      "text": "Hace un mes, durante una carrera de<n>práctica en la academia..."
    },
    {
      "name": "Umamusume honesta",
      "text": "¿Scarlet y Spe llegaron de últimas?!"
    },
    {
      "name": "Umamusume informada",
      "text": "Sé que Scarlet tuvo fiebre hace poco, pero me<n>pregunto por qué a Spe le fue tan\nmal. En realidad...<n>Parece que ha subido un poco de<n>peso,\npero..."
    },
    {
      "name": "Spe y Scarlet",
      "text": "¡Nooooo!"
    },
    {
      "name": "Special Week",
      "text": "<i>Uff... Uff... ¡Uf!</i> No puedo permitirme correr así<n>nunca más!\n¡Tengo que esforzarme más!"
    },
    {
      "name": "Special Week",
      "text": "¡Bah! Ya pasó un mes, ¡y todavía no<n>puedo salir de esta racha!\n¿Qué debería<n>hacer, mamá?"
    },
    {
      "name": "Madre de Spe",
      "text": "Escucha, tienes que dar un paso atrás y tomártelo<n>con calma! Por lo que me\nhas estado contando,<n>¿has estado entrenando sin parar, verdad?"
    },
    {
      "name": "Special Week",
      "text": "¡Y-yo <i>sí</i> he estado descansando bien! Duermo bien,<n>me relajo en\nel baño..."
    },
    {
      "name": "Spe's Mother",
      "text": "Eso no es lo que quiero decir! Me refiero a salir<n>a divertirte con tus\namigas para despejarte.<n>No has estado haciendo eso,<n>¿verdad?"
    },
    {
      "name": "Madre de Spe",
      "text": "Solo confía en mí! Inténtalo. Deja ir tooooodas<n>tus preocupaciones\npor un rato y tal vez<n>encuentres que eso resuelve\ntu problema."
    },
    {
      "name": "Special Week",
      "text": "Yo... Supongo que es cierto..."
    },
    {
      "name": "Special Week",
      "text": "P-pero si salgo con amigas ahora<n>antes de tener mi carrera\n¡Estaría evadiendo mis responsabilidades!"
    },
    {
      "name": "Daiwa Scarlet",
      "text": "Mamá me envió algo? Me pregunto qué<n>será."
    },
    {
      "name": "Monólogo",
      "text": "\"Espero que te guste el traje de baño que te conseguí.<n>Has estado tan\nocupada últimamente. Tómate tiempo para visitar la playa\no la piscina de vez en cuando, cariño. Con amor,\nMamá.\""
    },
    {
      "name": "Daiwa Scarlet",
      "text": "¡Guau! ¡Qué lindo traje de baño! \"Visitar la playa o la piscina,\" ¿eh?\nMe alegra que piense en mí, pero me pregunto por qué el<n>regalo repentino."
    },
    {
      "name": "Daiwa Scarlet",
      "text": "Ella siempre está tan ocupada con el trabajo y suele dejarme por mi cuenta,\nentonces… ¿por qué...? Oh..."
    },
    {
      "name": "Daiwa Scarlet",
      "text": "(¿Podría ser que ella sepa lo mal que me fue<n>en mi última\ncarrera de práctica?!)"
    },
    {
      "name": "Daiwa Scarlet",
      "text": "(Tal vez ella piense que no me estoy cuidando<n>por eso...\nNo,<n>estoy pensando demasiado. No es posible que ella<n>haya...)"
    },
    {
      "name": "Daiwa Scarlet",
      "text": "..."
    },
    {
      "name": "Daiwa Scarlet",
      "text": "¡Ñe! Definitivamente ganaré la próxima carrera y<n>me aseguraré de que\nella sepa ¡que quedé en primer lugar!"
    },
    {
      "name": "Special Week",
      "text": "<i>Suspira...</i> No puedo creer que terminé discutiendo<n>con mamá ayer..."
    },
    {
      "name": "Special Week",
      "text": "Uf, ¿qué estoy haciendo, perdiendo el tiempo en<n>la pista de carreras?\n¡Tengo que concentrarme! Hoy<n>voy a entrenar con toda!"
    },
    {
      "name": "Daiwa Scarlet",
      "text": "¡Tenía la sensación de que ella estaría aquí!\n¿Te gustaría<n>correr conmigo, tal vez?"
    },
    {
      "name": "Daiwa Scarlet",
      "text": "\"Desde el otro día en la práctica no he podido volver a mi forma,\nsin importar lo que haga. ¿Ha sido igual<n>para ti, Spe?\""
    },
    {
      "name": "Special Week",
      "text": "\"¡S-sí! Entre más lo pienso, más me<n>confundo con mi\nforma al<n>correr. Pero antes todo estaba bien...\""
    },
    {
      "name": "Daiwa Scarlet",
      "text": "\"Te entiendo. Estoy en la<n>misma situación. Por eso pensé que\nretarte a una carrera podría ayudarme a<n>volver a mi\nritmo, así que...\""
    },
    {
      "name": "Special Week",
      "text": "(Nubes de polvo, pasos retumbantes,<n>alguien adelante de mí... Sí,\n<i>así</i> es como se siente<n>una carrera! ¡Todo me vuelve!)"
    },
    {
      "name": "Special Week",
      "text": "(¡Muy bien! Ya casi llegamos a la cuarta<n>esquina! ¡Solo debo mover\nestas<n>piernas y brazos y alcanzar a Scarlet!)"
    },
    {
      "name": "Special Week",
      "text": "(Espera, ¿por qué no avanzo más rápido? ¿Cómo debo<n>mover mis\npiernas de nuevo? ¡Solo<n>sé que mi forma al correr se está perdiendo!)"
    },
    {
      "name": "Special Week",
      "text": "(¡Ay! La brecha entre nosotras se hará<n>más grande si no me apuro.\nTengo que cambiar<n>de marcha... ¡¿Cómo era que se hacía?!)"
    },
    {
      "name": "Special Week",
      "text": "(Oh nooo, ¡¿qué debo hacer?!)"
    },
    {
      "name": "Special Week",
      "text": "¡Gah!"
    },
    {
      "name": "Spe y Scarlet",
      "text": "<i>Jadeo... Jadeo...</i>"
    },
    {
      "name": "Maruzensky",
      "text": "Por Dios… sus posturas están por todos lados.\nHan perdido por completo la noción de su estilo al correr"
    },
    {
      "name": "Maruzensky",
      "text": "Tengo la impresión de que también olvidaron otras cosas en su\ndesesperación...Hmm, si ese es el caso..."
    },
    {
      "name": "Maruzensky",
      "text": "¡Oye, Spe! Conozco un sitio que te sacará<n>del hoyo y te devolverá a tu\nfantabulosa<n>forma. ¡Acompáñame a Burbulandia!"
    },
    {
      "name": "Special Week",
      "text": "¡¿De verdad hay un lugar así?!"
    },
    {
      "name": "Maruzensky",
      "text": "¡Claro que sí! Escuché de Fuji que tú y<n>Scarlet no han estado<n>muy bien últimamente,\nasí que<n>pensé que podríamos ir todos."
    },
    {
      "name": "Maruzensky",
      "text": "He alquilado un auto e invité a nuestra amiga<n>fanática del deporte, Ticket,\npara que nos acompañe,<n>así que estamos listos para irnos!"
    },
    {
      "name": "Maruzensky",
      "text": "Aun con eso, Scarlet rechazó la invitación. Dice que su rutina de\nentrenamiento ya está más que fijada. ¡Ja, ja!"
    },
    {
      "name": "Maruzensky",
      "text": "¿Y tú? ¿Te animas?"
    },
    {
      "name": "Special Week",
      "text": "(Si este centro de entrenamiento que Maruzensky<n>recomienda\nrealmente puede<n>ayudar a la gente a salir<n>de sus bajones,\nentonces quizás debería ir.)"
    },
    {
      "name": "Special Week",
      "text": "¡Cuenta conmigo!"
    },
    {
      "name": "Monólogo",
      "text": "Y así..."
    },
    {
      "name": "Maruzensky",
      "text": "¡Spe y Ticket, sujetense bien! ¡Lo que van a vivir en Burbulandia es pura magia!"
    },
    {
      "name": "Sweep Tosho",
      "text": "¿Magia? ¡Yo también voy a ese lugar<n>Burbu o como se llame!\nNadie<n>me va a detener!"
    },
    {
      "name": "Monólogo",
      "text": "Y ahora, habiendo llegado..."
    },
    {
      "name": "Special Week",
      "text": "Así que esto es Burbulandia."
    },
    {
      "name": "Special Week",
      "text": "Esperen, ¿realmente se puede entrenar<n>aquí? Es posible, ¿no?"
    }
  ]
}
