{
  "no_wrap": true,
  "text_block_list": [
    {
      "name": "Narita Brian",
      "text": "<i>Uff... Uff...</i> ¡No puedo creer que sea tan<n>fuerte!"
    },
    {
      "name": "Biwa Hayahide",
      "text": "...Brian."
    },
    {
      "name": "Narita Brian",
      "text": "Hermana..."
    },
    {
      "name": "Biwa Hayahide",
      "text": "Solo hay una explicación de por qué<n>prevalezco"
    },
    {
      "name": "Biwa Hayahide",
      "text": "Según datos pasados, una corredora clásica<n>nunca\nha"
    },
    {
      "name": "Biwa Hayahide",
      "text": "En cuanto al porqué, el año clásico es el<n>punto\nmedio"
    },
    {
      "name": "Biwa Hayahide",
      "text": "En resumen, tenía una ventaja<n>innegable. Yo"
    },
    {
      "name": "Biwa Hayahide",
      "text": "Por eso, dentro de un año, quiero<n>competir\ncontigo"
    },
    {
      "name": "Biwa Hayahide",
      "text": "Solo entonces, tras competir de nuevo,\npodré<n>decir de verdad"
    },
    {
      "name": "Narita Brian",
      "text": "Tch... Oh, qué generosa..."
    },
    {
      "name": "Narita Brian",
      "text": "Bien. Mejor que no intentes echarte\natrás.<n>Próximo"
    },
    {
      "name": "Biwa Hayahide",
      "text": "Jaja, no me retiraré. Soy quien te<n>desafia"
    },
    {
      "name": "Biwa Hayahide",
      "text": "Así que cuando llegue ese momento, da lo<n>mejor\nde ti"
    },
    {
      "name": "Narita Brian",
      "text": "¡Tráelo!"
    }
  ]
}