{
  "no_wrap": true,
  "text_block_list": [
    {
      "name": "Narita Taishin",
      "text": "¡Argh! ¡Qué demonios! ¡No pude <n>vencerte!"
    },
    {
      "name": "Narita Taishin",
      "text": "¡Maldición, maldición, maldición! <n><i>¡Hayahide, eres\n</i><i>tal</i> molestia!"
    },
    {
      "name": "Biwa Hayahide",
      "text": "Taishin, yo..."
    },
    {
      "name": "Biwa Hayahide",
      "text": "Hehe... ¡Jajaja!"
    },
    {
      "name": "Biwa Hayahide",
      "text": "¡Sí, tienes razón! ¡Ciertamente lo soy!"
    },
    {
      "name": "Winning Ticket",
      "text": "¡Eso no es justo!"
    },
    {
      "name": "Narita Taishin",
      "text": "¿Huh?"
    },
    {
      "text": "De repente escuchan a Winning<n> Ticket gritando\nmientras vuelven a la<n> academia."
    },
    {
      "name": "Winning Ticket",
      "text": "No es justo, no es justo, no es <i>justo, no <i>justoo!</i>\n<n></i>No es genial lo bien que se llevan ustedes dos!"
    },
    {
      "name": "Winning Ticket",
      "text": "¡Quiero correr con ustedes también!"
    },
    {
      "name": "Narita Taishin",
      "text": "Uh, solo tienes que culparte a ti<n> misma por\nlesionarte."
    },
    {
      "name": "Winning Ticket",
      "text": "¡Waaaaah!"
    },
    {
      "name": "Biwa Hayahide",
      "text": "Ahora, ahora. No hay necesidad de llorar."
    },
    {
      "name": "Biwa Hayahide",
      "text": "Las tres aún estamos en la Twinkle<n> Series."
    },
    {
      "name": "Biwa Hayahide",
      "text": "Lo que significa que podemos correr unas <n>contra\notras tan a menudo como queramos."
    },
    {
      "name": "Biwa Hayahide",
      "text": "¿Verdad?"
    },
    {
      "name": "Winning Ticket",
      "text": "Aww, ¡Hayahide!"
    },
    {
      "name": "Winning Ticket",
      "text": "¡Waaaah! ¡Eso <i>es</i> correcto!"
    },
    {
      "name": "Winning Ticket",
      "text": "Oooh, ¡lo sé! ¡Corramos todas en el<n> Tenno Sho de\notoño!"
    },
    {
      "name": "Winning Ticket",
      "text": "¡Será una reunión de BNW!"
    },
    {
      "name": "Narita Taishin",
      "text": "¿En serio no te da vergüenza usar<n> ese nombre?"
    },
    {
      "text": "Las tres juran correr juntas en<n> el Tenno Sho de\notoño antes de <n>separarse."
    }
  ]
}