{
  "no_wrap": true,
  "text_block_list": [
    {
      "name": "Monólogo",
      "text": "Habiendo ganado el Tenno Sho de otoño,<n> Mayano Top\nGun ha crecido para ser una <n>corredora que\nrealmente hace rugir de emoción<n> a sus fans."
    },
    {
      "name": "Monólogo",
      "text": "Unos días después mientras entrena, ve a la<n>\ncompañera de Narita Brian corriendo <n>con Symboli\nRudolf."
    },
    {
      "name": "Monólogo",
      "text": "Con la imagen de Narita Brian <n>brillando\nintensamente en su mente, jura darlo<n> todo en el\nArima Kinen."
    }
  ]
}