{
  "no_wrap": true,
  "text_block_list": [
    {
      "name": "El Condor Pasa",
      "text": "¡Grass, gané! ¡Gané! ¿Me viste?"
    },
    {
      "name": "El Condor Pasa",
      "text": "¿Estás bien?"
    },
    {
      "name": "Grass Wonder",
      "text": "Sí. Y sí que te vi ganar desde la oscuridad sin\nfin de ese agujero negro."
    },
    {
      "name": "Machos Mercenarios",
      "text": "Te haces el tranquilo, pero eres duro como una\npiedra, Grass."
    },
    {
      "name": "Uma Lord Golshi",
      "text": "¡Jajajaja! Si crees que este juego se acabó,\nentonces estás muy equivocado!"
    },
    {
      "name": "Uma Lord Golshi",
      "text": "¿No lo sabes? ¡Todo RPG que se precie tiene un\njefe extra aún más difícil!"
    },
    {
      "name": "Grass Wonder",
      "text": "Basta de fanfarronería, Golshi."
    },
    {
      "name": "Grass Wonder",
      "text": "Solo hay tres Umamusume en este mundo. ¿Cómo\npodría haber otro oponente más fuerte que tú?"
    },
    {
      "name": "Uma Lord Golshi",
      "text": "Hay <i>un</i> oponente así, y está justo frente a ti.\n¿No puedes verlo?"
    },
    {
      "name": "El Condor Pasa",
      "text": "¡No! Este lugar está bien desolado... No hay nada\nmás que tú y tu castillo!"
    },
    {
      "name": "Uma Lord Golshi",
      "text": "Aha, así que <i>sí</i> lo ves después de todo. ¡Contempla\nal verdadero jefe final!"
    },
    {
      "name": "Grass Wonder",
      "text": "¿¡Eh?! ¿Quieres decir que el jefe final es..."
    },
    {
      "name": "Uma Lord Golshi",
      "text": "¡Así es! La fortaleza de la Uma Lord no es un\ncastillo cualquiera. ¡He estado alimentándola con\nextracto de zanahoria extra-nutritivo para\naumentar su energía!"
    },
    {
      "name": "Uma Lord Golshi",
      "text": "¡Arriba, Golshi Castillo! ¡Muéstranos tu cuarta\nforma!"
    },
    {
      "name": "Castillo Golshi",
      "text": "¡Grrr! ¡Gold Shiiiiip!"
    },
    {
      "name": "Uma Lord Golshi",
      "text": "¡Mwahahaha! Entonces, ¿qué te parece <i>esto?</i>¿Pueden\ntus puños derribar a este? ¡Lo creeré cuando lo\nvea! Kekekeke!Naaanana, naaana!"
    },
    {
      "name": "Uma Lord Golshi",
      "text": "¡Vamos, Golshi Castle! ¡Date prisa y destrózalos\npor completo! ¡Qué mala suerte para ti, este juego\nque estás jugando es imposible de ganar!"
    },
    {
      "name": "El Condor Pasa",
      "text": "Grass, no creo que mis habilidades de peleadora le\nganen a esta ¡esta!"
    },
    {
      "name": "Grass Wonder",
      "text": "Mi Rayo Angelical tampoco hará mucho contra una\nfortaleza. ¿Qué debemos hacer?"
    },
    {
      "name": "Mercenarios Machos",
      "text": "¡Chicas! ¿Sus poderes de Umamusume no pueden hacer\nalgo para que funcione?"
    },
    {
      "name": "Grass Wonder",
      "text": "Nuestros poderes de Uma Musume... Podríamos\nintentarlo. Si no podemos confiar en nuestros\npoderes de clase, entonces no nos queda otra..."
    },
    {
      "name": "Grass Wonder",
      "text": "¡Espera! Ahora que lo mencionas..."
    },
    {
      "name": "Abuela Mística",
      "text": "\"La encarnación de la fantasía mirará este mundo\ndesde los cielos. Con un poder innato y atronador,\nella le propinará al señor demonio un golpe de\ndestrucción y felicidad por igual.\""
    },
    {
      "name": "Grass Wonder",
      "text": "\"Poder innato y atronador\". Si lo interpretamos\ncomo una habilidad que las Umamusume adquieren\nnaturalmente..."
    },
    {
      "name": "Grass Wonder",
      "text": "Mira desde arriba este mundo... descarga una\ndestrucción atronadora... sobre el señor\ndemonio..."
    },
    {
      "name": "Grass Wonder",
      "text": "¡Ya sé! ¡Lo descubrí! ¡Creo que podemos derrotar\neste castillo!"
    },
    {
      "name": "El Condor Pasa",
      "text": "¡Lo entendiste, Grass?! ¿¡Qué se supone que debemos\nhacer?!"
    },
    {
      "name": "Grass Wonder",
      "text": "Chicos. ¿Me podrían dar alguna de esas pociones de\ncrecimiento que usaron? Las que te hicieron\ngigante."
    },
    {
      "name": "Mercenarios Machos",
      "text": "¿¡Eh? Pues, claro. Uno de estos, ¿verdad?!"
    },
    {
      "name": "Grass Wonder",
      "text": "¡Más, por favor! ¡Necesito todo lo que tienes!"
    },
    {
      "name": "Machos Mercenarios",
      "text": "¿Todo? Si bebes <i>tanto</i>, terminarás escupiendo\nsangre por la nariz en un viaje de ida a\nHeavenheim..."
    },
    {
      "name": "Grass Wonder",
      "text": "Si fuera humano, tal vez, pero no es nada que una\nUmamusume no pueda soportar! ¡Apúrate!"
    },
    {
      "name": "El Condor Pasa",
      "text": "¡Guau, Grass?!"
    },
    {
      "name": "Grass Wonder",
      "text": "Jeje. Qué buena vista desde aquí arriba. ♪ La\nUmamusume gigante, pasando."
    },
    {
      "name": "Grass Wonder",
      "text": "Ummm... Quizás crecí <i>muchísimo. </i>Ya ni siquiera\npuedo ver el castillo de Golshi."
    },
    {
      "name": "Uma Lord Golshi",
      "text": "¡Oye, grandulón! ¡Basta! ¡Aléjate de mí! ¡Mira por\ndónde caminas!"
    },
    {
      "name": "Grass Wonder",
      "text": "Seguro que estaba por aquí..."
    },
    {
      "name": "Castillo Golshi",
      "text": "¡Ngh?! ¡Gooold Shiiip!"
    },
    {
      "name": "Uma Lord Golshi",
      "text": "¡Noooooo! ¡Mi castillo Golshi HG a escala 1:1!"
    },
    {
      "name": "Grass Wonder",
      "text": "Oh no... ¿Fui <i>yo</i> la que hizo eso? Lo siento, no lo\nvi ahí."
    },
    {
      "name": "El Condor Pasa",
      "text": "Seguro que lo destrozó de frente para alguien que\n\"no lo vio\"."
    },
    {
      "name": "Abuela Mística",
      "text": "¡Ohhh, un golpe atronador desde lo alto! Es tal\ncomo la leyenda predijo."
    },
    {
      "name": "Abuela Mística",
      "text": "Pero, espera. La leyenda decía que tanto la\ndestrucción como la felicidad serían entregadas al\nseñor demonio."
    },
    {
      "name": "El Condor Pasa",
      "text": "¿Qué? Entiendo lo de la destrucción, pero ¿y la\nfelicidad?"
    },
    {
      "name": "Uma Lord Golshi",
      "text": "Deja de hacer el tonto. ¿¡Crees que esto es algún\ntipo de juego?! Pues, te voy a mostrar..."
    },
    {
      "name": "Uma Lord Golshi",
      "text": "¡Oye, musculoso! ¡Suelta el resto de esas pociones\ngigantes!"
    },
    {
      "name": "Machos Mercenarios",
      "text": "¡Hey! ¿Qué te crees que estás haciendo?"
    },
    {
      "name": "Uma Lord Golshi",
      "text": "¡Aún no me rindo! ¡Aquí viene Gigante Golshi,\nrecién salida de la tierra de la luz!"
    },
    {
      "name": "Grass Wonder",
      "text": "¿Eh? ¿Tú también te estás convirtiendo en un\ngigante?"
    },
    {
      "name": "Uma Lord Golshi",
      "text": "¡Por supuesto! ¡No voy a dejar que esta\noportunidad se me escape! ¡Ahora, ven aquí! Vamos\nsssss"
    },
    {
      "name": "Grass Wonder",
      "text": "E-espera, yo no... ¿por qué se cayó?"
    },
    {
      "name": "Uma Lord Golshi",
      "text": "¡No me <i>caí!</i> Estoy tumbada. Con ese poder de\npiernas que tienes, apuesto a que podrías ayudarme\nmucho."
    },
    {
      "name": "Uma Lord Golshi",
      "text": "Ahora, necesito que pises sobre mí. Justo aquí,\nalrededor de mis hombros. Tu relámpago no hizo\nnada por mis calambres, pero un buen masaje fuerte\npodría ayudar."
    },
    {
      "name": "Grass Wonder",
      "text": "Ah, oh. ¿Y esto, entonces?"
    },
    {
      "name": "Uma Lord Golshi",
      "text": "Ahhhh... Ese es el punto. Sí, así... Dámelo con\nfuerza... más fuerte... ¡Oh!"
    },
    {
      "name": "Abuela Mística",
      "text": "Oh... ¡Destrucción <i>y</i> felicidad! ¡Hemos sido\nsalvados! ¡Nuestro mundo ha sido salvado!"
    },
    {
      "name": "El Condor Pasa",
      "text": "Y pensar... Supongo que tiene sentido que una\nclériga pueda curar hombros rígidos también..."
    }
  ]
}