{
  "no_wrap": true,
  "text_block_list": [
    {
      "name": "Mejiro Ryan",
      "text": "Lo logré... Entrenador, ¡lo logré!"
    },
    {
      "name": "Mejiro Ryan",
      "text": "¡Cumplí mi primera promesa! ¡Gané <n>el Takarazuka\nKinen!",
      "choice_data_list": [
        "¡Felicidades! Ahora ven aquí."
      ]
    },
    {
      "name": "Monólogo",
      "text": "Jalo a Mejiro Ryan, que está haciendo<n> una pose de\nvictoria, a un lugar más<n> adecuado."
    },
    {
      "name": "Mejiro Ryan",
      "text": "¡Gracias por venir a verme <n>hoy, todos!"
    },
    {
      "name": "Mejiro Ryan",
      "text": "¡Pude devolverles todo el apoyo <n>que me han dado!\n¡Pero aún necesito su<n> ayuda, porque también voy a\nganar<n> el Arima Kinen!"
    },
    {
      "name": "Mejiro Ryan",
      "text": "¡Gracias por todo!"
    },
    {
      "name": "Mejiro McQueen",
      "text": "Dios mío. ¿Mostrar los músculos es <n>un saludo\nrespetable? Esta chica..."
    },
    {
      "name": "Mejiro McQueen",
      "text": "Ryan, voy a confiarte las carreras<n> de media\ndistancia de Mejiro por un<n> tiempo."
    },
    {
      "name": "Mejiro Ryan",
      "text": "¿Q-qué—¿a mí?"
    },
    {
      "name": "Mejiro McQueen",
      "text": "Ahora que he perdido hoy, mi plan es <n>enfocarme en\nser una fondista."
    },
    {
      "name": "Mejiro McQueen",
      "text": "Por supuesto, <i>hay una distancia </i>donde ambas<n>\npodemos mostrar adecuadamente nuestras<n> fortalezas."
    },
    {
      "name": "Mejiro Ryan",
      "text": "¿Qué distancia es esa?"
    },
    {
      "name": "Mejiro McQueen",
      "text": "2,500 metros, diría yo."
    },
    {
      "name": "Mejiro McQueen",
      "text": "Encontémonos en el ilustre Hipódromo de<n> Nakayama,\npara el Arima Kinen de fin<n> de año."
    },
    {
      "name": "Mejiro McQueen",
      "text": "Obviamente serás una estrella aún más grande <n>de lo\nque eres ahora. Espero que crezcas para\n<n>convertirte en una exquisita dama."
    },
    {
      "name": "Mejiro Ryan",
      "text": "Una exquisita dama..."
    },
    {
      "name": "Mejiro Ryan",
      "text": "E-Entrenador... ¿Cómo se supone que debo<n> hacer eso\nen solo seis meses?!"
    },
    {
      "name": "Monólogo",
      "text": "Puede ser una tarea más alta que convertirte en<n>\nuna estrella corredora... Pero tendremos que ver\nqué<n> podemos hacer."
    }
  ]
}