{
  "no_wrap": true,
  "text_block_list": [
    {
      "name": "Monólogo",
      "text": "Mientras regreso de una salida con Mejiro<n> Ryan..."
    },
    {
      "name": "Ines Fujin",
      "text": "¡Allí estás, Ryan! ¡Rápido, rápido,<n> ven aquí!"
    },
    {
      "name": "Mejiro Ryan",
      "text": "¿Eh? ¿Q-qué está pasando?!"
    },
    {
      "name": "Monólogo",
      "text": "Ines Fujin aparece de repente y se <n>lleva a Mejiro\nRyan. Corro tras ellas para<n> ver qué ocurre."
    },
    {
      "name": "Ines Fujin",
      "text": "¡Hola a todos! ¡Encontré a Ryan!"
    },
    {
      "name": "Umamusume A",
      "text": "¡Buen trabajo, Ines! ¡Rápido, Ryan, a la<n> cancha!"
    },
    {
      "name": "Mejiro Ryan",
      "text": "¿Qué es esto? ¿Un partido de voleibol?"
    },
    {
      "name": "Ines Fujin",
      "text": "¡Así es! Tenemos un partido <n>interclases. ¡Ha sido\nun juego de ida y <n>vuelta!"
    },
    {
      "name": "Ines Fujin",
      "text": "¡Y llegas justo a tiempo para ser nuestra sorpresa<n>\ncomo servidora de emergencia!"
    },
    {
      "name": "Mejiro Ryan",
      "text": "B-bueno, no sé realmente qué tan bien lo<n> haré..."
    },
    {
      "name": "Mejiro Ryan",
      "text": "¡Pero si me necesitas, tengo que intentarlo!<n> ¡Dame\nun momento!"
    },
    {
      "name": "Mejiro Ryan",
      "text": "Vale, estoy lista. ¡Reanudemos el partido!"
    },
    {
      "name": "Umamusume A",
      "text": "¡Vamos, Ryan! ¡Ace ese saque!"
    },
    {
      "name": "Mejiro Ryan",
      "text": "Jeje, ¡haré lo que pueda! ¡No contengan<n> los\nánimos!"
    },
    {
      "name": "Mejiro Ryan",
      "text": "¡Allá vamos! Concéntrate..."
    },
    {
      "name": "Ines Fujin",
      "text": "Siempre puedes contar con Ryan para que <n>se\nentusiasme, jeje. ♪"
    },
    {
      "name": "Monólogo",
      "text": "Suena el silbato y Mejiro Ryan<n> ejecuta su saque..."
    },
    {
      "name": "Mejiro Ryan",
      "text": "¡Haah!"
    },
    {
      "name": "Monólogo",
      "text": "<i>¡Pum!</i>"
    },
    {
      "name": "Ines Fujin",
      "text": "No solo hiciste un saque directo, ¡sino<n> que\ntambién mostraste un gran ataque<n> y defensa\ndespués!"
    },
    {
      "name": "Ines Fujin",
      "text": "<i>¡Yo <i>sabía</i> que lo lograrías! ¡Eres una diosa <n>de la\nvictoria en la vida real! ¡Wuju!"
    },
    {
      "name": "Umamusume A",
      "text": "¡En serio! ¡Qué gran idea fue<n> meterte en el juego!"
    },
    {
      "name": "Mejiro Ryan",
      "text": "Jaja, ¡me alegra escucharlo!",
      "choice_data_list": [
        "Eres muy popular.",
        "Eres muy popular.",
        "¡Me enorgullece ser tu entrenador!",
        "¡Me enorgullece ser tu entrenador!"
      ]
    },
    {
      "name": "Mejiro Ryan",
      "text": "Jaja, ¡me alegra escucharlo!",
      "choice_data_list": [
        "Eres muy popular.",
        "Eres muy popular.",
        "¡Me enorgullece ser tu entrenador!",
        "¡Me enorgullece ser tu entrenador!"
      ]
    },
    {
      "name": "Ines Fujin",
      "text": "¡Por supuesto que lo es! ¡Ryan es <n>nuestra\ninspiración—¡amada por todas!"
    },
    {
      "name": "Ines Fujin",
      "text": "¿Verdad?"
    },
    {
      "name": "Compañeras de clase",
      "text": "¡Sí! ¡Ryan es nuestra heroína!"
    },
    {
      "name": "Mejiro Ryan",
      "text": "Vaya, eso es un poco vergonzoso de <n>escuchar,\npero... ¡gracias! ¡Jeje!"
    },
    {
      "name": "Mejiro Ryan",
      "text": "¡Haré lo posible por no defraudar a nadie!"
    },
    {
      "name": "Monólogo",
      "text": "Incluso como suplente inesperada,<n> la presencia\nactiva de Mejiro Ryan deja<n> claro por qué es tan\npopular."
    },
    {
      "name": "Mejiro Ryan",
      "text": "¡Muchas gracias! Jeje, creo que me estoy<n>\nsonrojando..."
    },
    {
      "name": "Ines Fujin",
      "text": "¡Wuju! ¡Tu entrenador es muy atrevido al<n> decir eso\ndelante de todos!"
    },
    {
      "name": "Ines Fujin",
      "text": "<i>¡Silbato!</i> ¿Verdad, chicas?"
    },
    {
      "name": "Compañeras de clase",
      "text": "<i>¡Silbato!</i> ¡Sí! ¡Todas lo escuchamos!"
    },
    {
      "name": "Mejiro Ryan",
      "text": "¿¡Qué!? N-no, no es así! ¡Denos un <n>respiro aquí!"
    },
    {
      "name": "Monólogo",
      "text": "Rodeada por sus compañeras de clase, Mejiro<n> Ryan\nestá un poco avergonzada, pero es evidente<n> que es\npopular como alguien en quien <n>pueden confiar."
    }
  ]
}