{
  "no_wrap": true,
  "text_block_list": [
    {
      "name": "Mejiro McQueen",
      "text": "Ay... ¿Cómo llegué aquí?"
    },
    {
      "name": "Mejiro McQueen",
      "text": "Pensar que yo, de todas las personas, pude <n>haber\nestado tan distraída."
    },
    {
      "name": "Mejiro McQueen",
      "text": "¿Oh?"
    },
    {
      "name": "Mejiro McQueen",
      "text": "La estatua de las Tres Diosas... El <n>ambiente a su\nalrededor se siente... diferente de<n> lo usual."
    }
  ]
}