{
  "no_wrap": true,
  "text_block_list": [
    {
      "name": "Monólogo",
      "text": "Noto una gran multitud mientras me dirijo a la\npista de entrenamiento y decido ir a ver qué es lo\nque atrae tanta atención."
    },
    {
      "name": "Comentarista Umamusume",
      "text": "¡Desafiantes! ¿Están listos para el combate?"
    },
    {
      "name": "Comentarista Umamusume",
      "text": "¡Aquí vienen los representantes de las residencias\nMiho y Ritto! ¡Tomen sus puestos!"
    },
    {
      "name": "Mejiro Bright",
      "text": "Jeje. ♪ Mi querida hermana, puedo estar en deuda\ncontigo ya que siempre me has ayudado, pero eso no\nme impedirá darle todo a este desafío."
    },
    {
      "name": "Mejiro Ryan",
      "text": "Je. Me gusta escuchar eso. ¡No esperes que yo\ntampoco vaya a ser fácil contigo!"
    },
    {
      "name": "Residentes de la Residencia Ritto",
      "text": "¡Vamos, Bright, vamos!"
    },
    {
      "name": "Residentes de la Residencia Miho",
      "text": "Ryan, ¡queremos ver esos músculos tuyos!",
      "choice_data_list": [
        "¿Qué está pasando aquí?",
        "¿Qué está pasando aquí?"
      ]
    },
    {
      "name": "Mejiro Ryan",
      "text": "¡Es una batalla entre las residencias! De vez en\ncuando, las residencias Miho y Ritto se juntan\npara una pelea amistosa."
    },
    {
      "name": "Mejiro Bright",
      "text": "Realmente es todo por espectáculo, pero también es\nmi oportunidad de probarle a Ryan cuánto he\ncrecido, por eso perder no es una opción."
    },
    {
      "name": "Comentarista Umamusume",
      "text": "¡Muy bien! Esta vez, nuestro enfrentamiento\nprogramado de residencias será una carrera de\ndeshacerse de la basura."
    },
    {
      "name": "Comentarista Umamusume",
      "text": "Por aquí, tenemos una montaña de bolsas de basura\npara cada residencia. ¡El primer representante en\ndeshacerse de toda su basura gana!"
    },
    {
      "name": "Comentarista Umamusume",
      "text": "¡Desafiantes! En sus marcas... ¡Listos... YA!"
    },
    {
      "name": "Mejiro Ryan",
      "text": "¡Oh, sí! ¡Mis bíceps y tríceps están cantando!\n¡Déjame agarrar más!"
    },
    {
      "name": "Comentarista Umamusume",
      "text": "¡Miren a Mejiro Ryan usando sus músculos para\nllevar una gran cantidad de bolsas a la vez! ¡Es\ntan rápida!"
    },
    {
      "name": "Comentarista Umamusume",
      "text": "¡Veamos cómo van las cosas en el lado de Mejiro\nBright!"
    },
    {
      "name": "Mejiro Bright",
      "text": "Uf. Ustedes, bolsas, se veían tan lindas e\ninofensivas todas acurrucadas juntas, pero son\nbastante pesadas, ¿verdad?"
    },
    {
      "name": "Comentarista Umamusume",
      "text": "¡Parece estar luchando con la carga\ninesperadamente pesada! ¡Comenzamos a ver que se\nforma una brecha entre el progreso de las\ndesafiantes!"
    },
    {
      "name": "Residente de la Residencia Miho A",
      "text": "Jeje. Ya lo tenemos en la bolsa."
    },
    {
      "name": "Residente de la Residencia Miho B",
      "text": "¿Levantar cosas pesadas? Ryan nació para este\ndesafío."
    },
    {
      "name": "Mejiro Ryan",
      "text": "(Uf... ¡Voy por la mitad! ¡También voy muy por\ndelante de Bright!)"
    },
    {
      "name": "Mejiro Ryan",
      "text": "(Eso no significa que pueda bajar el ritmo.\nConozco a Bright y no es de las que se rinden.)"
    },
    {
      "name": "Mejiro Ryan",
      "text": "(Ella puede marchar a un ritmo más lento que todos\nlos demás, pero...)"
    },
    {
      "name": "Mejiro Ryan",
      "text": "(No importa cuánto se atrase, siempre encuentra la\nmanera de cerrar la brecha al final.)"
    },
    {
      "name": "Mejiro Ryan",
      "text": "¡No puedo bajar la guardia! ¡No si quiero ganar\nesto!"
    },
    {
      "name": "Mejiro Ryan",
      "text": "Ngh... <i>Jadeando... Jadeando...</i>"
    },
    {
      "name": "Residente de la Residencia Miho A",
      "text": "Oye, ¿no soy solo yo, o el ritmo de Ryan ha\ndisminuido mucho?"
    },
    {
      "name": "Residente de la Residencia Miho B",
      "text": "Sí... Me pregunto qué pasa?"
    },
    {
      "name": "Monólogo",
      "text": "Correr de un lado a otro con cargas tan pesadas se\nha convertido en ejercicio anaeróbico, y el\nesfuerzo está desgastando gradualmente su\nresistencia."
    },
    {
      "name": "Monólogo",
      "text": "Mejiro Bright, por otro lado..."
    },
    {
      "name": "Mejiro Bright",
      "text": "Arriba, arriba, arriba. Uf. Creo que finalmente le\nhe agarrado el truco a esto."
    },
    {
      "name": "Residente del Dormitorio Ritto A",
      "text": "¡Bright sigue yendo al mismo ritmo con el que\nempezó! ¡Esta victoria podría ser para cualquiera!"
    },
    {
      "name": "Mejiro Bright",
      "text": "(No te fijes en lo que pasa a tu alrededor y solo\ntómate las cosas con calma...)"
    },
    {
      "name": "Mejiro Bright",
      "text": "(Solo tengo que concentrarme en hacer lo que puedo\ne ir a mi propio ritmo. Mientras lo mantenga...)"
    },
    {
      "name": "Mejiro Bright",
      "text": "(El camino se abrirá. Un brote florecerá. Entonces\npodré cerrar la brecha entre todos los que están\ndelante de mí y superarlos...)"
    },
    {
      "name": "Mejiro Bright",
      "text": "(Llegué hasta aquí creyendo en mí misma. Por\neso...)"
    },
    {
      "name": "Mejiro Bright",
      "text": "¡El verdadero desafío comienza ahora, Ryan!"
    },
    {
      "name": "Mejiro Ryan",
      "text": "¡Acepto! ¡No te voy a perder, Bright!"
    },
    {
      "name": "Comentarista Umamusume",
      "text": "¡No puedo creer lo que veo! Han llegado codo con\ncodo, ¡y ambas están en su última bolsa de basura!\nPero ¿quién regresará primero?!"
    },
    {
      "name": "Residentes de la Residencia Miho",
      "text": "¡Vamos, Ryyaaan!"
    },
    {
      "name": "Mejiro Ryan",
      "text": "Raaaaah!"
    },
    {
      "name": "Residentes de la Residencia Ritto",
      "text": "¡Tú puedes, Bright!"
    },
    {
      "name": "Mejiro Bright",
      "text": "¡Yaaah!"
    },
    {
      "name": "Mejiro Ryan",
      "text": "<i>Jadeo... Jadeo... Jadeo...</i>"
    },
    {
      "name": "Mejiro Bright",
      "text": "<i>Jadeo... Jadeo... Jadeo...</i>"
    },
    {
      "name": "Comentarista Umamusume",
      "text": "¡Llega en primer lugar por un pelo Ryan! ¡La\nvictoria de hoy es para la Residencia Miho!"
    },
    {
      "name": "Mejiro Ryan",
      "text": "¡Uf! ¡Lo logré!"
    },
    {
      "name": "Mejiro Bright",
      "text": "Perdí por un solo paso. Pude enfrentarme bien\ncontra Ryan, pero..."
    },
    {
      "name": "Residentes de la Residencia Miho",
      "text": "¡Felicidades, Ryan!"
    },
    {
      "name": "Residentes de la Residencia Ritto",
      "text": "¡Buen trabajo, Bright! ¡Te viste muy genial allá\nafuera!"
    },
    {
      "name": "Monólogo",
      "text": "Los espectadores reunidos les dan una ronda\nruidosa de aplausos, completamente satisfechos con\nsu reñida competencia."
    },
    {
      "name": "Mejiro Bright",
      "text": "Debería haber sabido que este sería el resultado,\nconsiderando tu fuerza y velocidad, Ryan."
    },
    {
      "name": "Mejiro Bright",
      "text": "La culminación de todo tu trabajo diario realmente\nvalió la pena. Mi respeto por ti ha crecido mucho\nmás profundo."
    },
    {
      "name": "Mejiro Ryan",
      "text": "Jeje. ¡Podría decir lo mismo de ti!"
    },
    {
      "name": "Mejiro Ryan",
      "text": "Sabía que al final vendrías por mí, pero nunca\nesperé que te acercaras tanto."
    },
    {
      "name": "Mejiro Bright",
      "text": "Puede que hayas ganado esta vez, pero daré vuelta\ntablas en nuestra próxima pelea."
    },
    {
      "name": "Mejiro Bright",
      "text": "Lo que significa que tengo que pulir mis\nhabilidades para deshacerme de la basura."
    },
    {
      "name": "Mejiro Bright",
      "text": "¡Lo sé! Puedo empezar mi nuevo entrenamiento\nllevando toda la basura de la Residencia Ritto. ♪"
    },
    {
      "name": "Mejiro Ryan",
      "text": "¿Huh? ¿En serio vas a empezar tu entrenamiento\nahora mismo? ¡Bright, estás loca..."
    }
  ]
}