{
  "no_wrap": true,
  "text_block_list": [
    {
      "name": "Fine Motion",
      "text": "Oye, Groove. Estaba revisando <n>la ropa que me\nenviaron mis padres y<n> creo que algunas te\nquedarían <n>perfectas."
    },
    {
      "name": "Air Groove",
      "text": "...¿En serio?"
    },
    {
      "name": "Air Groove",
      "text": "Mmm, la verdad no creo que me quede<n> muy bien..."
    },
    {
      "name": "Fine Motion",
      "text": "¡Vamos, no pierdes nada con probarlo! Solo<n> esta\nvez. ¿Lo harás por mí, verdad?<n> ¡Genial!"
    },
    {
      "name": "Air Groove",
      "text": "E-espera, ¡yo nunca dije que lo haría! <n><i>Ugh, <i>vale.</i> Como quieras."
    },
    {
      "name": "Air Groove",
      "text": "¿¡Eh?! ¿Qué está pasando?!"
    },
    {
      "name": "Air Groove",
      "text": "No puedo... entrar. Imposible... <n>¿Habré\nengordado?!"
    },
    {
      "name": "Air Groove",
      "text": "Tal vez sea cierto que he sido demasiado permisiva<n>\ncon mi entrenamiento últimamente..."
    },
    {
      "name": "Air Groove",
      "text": "Necesito hablar con mi entrenador<n> y pedirle un\nrégimen más exigente."
    },
    {
      "name": "Fine Motion",
      "text": "¡Espera, Groove! ¡Vuelve! ¡Acabo<n> de darme\ncuenta—estos son de cuando<n> era una niña!"
    },
    {
      "name": "Fine Motion",
      "text": "No me escuchó... Bueno, se lo diré<n> cuando regrese."
    },
    {
      "name": "Monólogo",
      "text": "Aunque pudo haber comenzado como<n> un malentendido,\nel nuevo régimen de <n>Air Groove de todos modos\ntiene el efecto<n> deseado."
    }
  ]
}