{
  "no_wrap": true,
  "text_block_list": [
    {
      "name": "Monólogo",
      "text": "Mientras Super Creek lucha con su salud, un\nsalvador inesperado viene a rescatarla durante el\ncampamento de verano."
    },
    {
      "name": "???",
      "text": "¡Jajaja! Parece que realmente estás luchando allí,\n¡Creek!"
    },
    {
      "name": "???",
      "text": "¡Bueno, estoy aquí para darte un verdadero\ndesafío! ¡Eso es, yo—",
      "choice_data_list": [
        "¡Ah, es un niño local!"
      ]
    },
    {
      "name": "Tamamo Cross",
      "text": "¡No lo soy! ¡Soy la mejor amiga de Creek, Tamamo\nCross! ¡Pero sabes, tienes un gran timing cómico!"
    },
    {
      "name": "Tamamo Cross",
      "text": "¡Correcto! Vamos, Creek. Intenta vencerme en una\ncarrera por la playa!"
    },
    {
      "name": "Super Creek",
      "text": "<i>Huff... pant...</i> Mis... piernas..."
    },
    {
      "name": "Tamamo Cross",
      "text": "¿Ya estás en las últimas, eh? Pero sabes qué\nnecesitas en un momento como este?"
    },
    {
      "name": "Tamamo Cross",
      "text": "¡Empuje! ¡No tienes ganas de seguir porque estás\nsin motivación!"
    },
    {
      "name": "Tamamo Cross",
      "text": "¿Qué vas a hacer con un empuje tan débil? Si\nquieres consentir a tu entrenador, ¡entonces da lo\nmejor de ti!"
    },
    {
      "name": "Super Creek",
      "text": "Por el Entrenador... Por el Entrenador..."
    },
    {
      "name": "Super Creek",
      "text": "Gahhh..."
    },
    {
      "name": "Tamamo Cross",
      "text": "¿Eh? ¿De qué se trata todo esto?"
    },
    {
      "name": "Monólogo",
      "text": "...Pensé que esto podría pasar."
    },
    {
      "name": "Tamamo Cross",
      "text": "Hmm, raro. Pensé que solo necesitaba un poco de\nempuje."
    },
    {
      "name": "Tamamo Cross",
      "text": "A este ritmo, nunca me vas a vencer.",
      "choice_data_list": [
        "¿Tienes un momento, Creek?"
      ]
    },
    {
      "name": "Super Creek",
      "text": "<i>Huff... wheeze...</i> Lo siento... Lo siento mucho..."
    },
    {
      "name": "Super Creek",
      "text": "Quiero hacer lo mejor por ti... pero simplemente\nno tengo la energía...",
      "choice_data_list": [
        "Si no puedes hacerlo sola, ¿por qué no corremos\ncomo equipo?"
      ]
    },
    {
      "name": "Super Creek",
      "text": "¿Eh? ¿Como equipo?"
    },
    {
      "name": "Tamamo Cross",
      "text": "¿Qué es eso ahora? ¿Vosotros dos vais a correr un\nrelevo?"
    },
    {
      "name": "Tamamo Cross",
      "text": "Raro... No veo cómo un entrenador va a ser de\nmucha ayuda en una carrera de Umamusume."
    },
    {
      "name": "Tamamo Cross",
      "text": "Pero da igual. Te daré un pequeño hándicap\nentonces. ¡Puedes tener ventaja!"
    },
    {
      "name": "Monólogo",
      "text": "Super Creek debería ser la última posta, así que\nyo empezaré con un sprint a fondo."
    },
    {
      "name": "Tamamo Cross",
      "text": "¿¡Whaaa!? ¡Eres bastante rápida! ¡Nada mal!"
    },
    {
      "name": "Super Creek",
      "text": "¿Desde cuándo estás tan en forma, Entrenador?"
    },
    {
      "name": "Monólogo",
      "text": "Mi propia fuerza y resistencia han aumentado con\nel tiempo que he pasado con Super Creek—lo que\nsignifica..."
    },
    {
      "name": "Tamamo Cross",
      "text": "Guau, eso servirá para tu hándicap. Si vas a\nesforzarte tanto, entonces yo también voy a\nponerme serio!"
    },
    {
      "name": "Monólogo",
      "text": "Tamamo Cross me adelanta en un instante, pero yo\nsigo corriendo, exprimiendo cada última onza de\nenergía que tengo..."
    },
    {
      "name": "Super Creek",
      "text": "¡Vamos, Entrenador! ¡Ven a mí!"
    },
    {
      "name": "Super Creek",
      "text": "¡Entrenadorrr!"
    },
    {
      "name": "Monólogo",
      "text": "Aturdido y sin aliento, le paso el testigo a Super\nCreek. En ese momento..."
    },
    {
      "name": "Super Creek",
      "text": "¡Solo espera, Tamtam! ¡YAAAAAHHHHH!"
    },
    {
      "name": "Tamamo Cross",
      "text": "¡Whoooa! ¿Qué pasa con la energía de Creek?!"
    },
    {
      "name": "Super Creek",
      "text": "Puedo ganar. Voy a ganar. <i>Voy a</i> ganar!"
    },
    {
      "name": "Super Creek",
      "text": "¡Con nuestros poderes combinados, no hay nada que\nno podamos hacer!"
    },
    {
      "name": "Monólogo",
      "text": "Para cuando me recupero, el sol ya se ha puesto.\n¿Y el resultado?"
    },
    {
      "name": "Tamamo Cross",
      "text": "Oh, rayos. Me ganaste, sin más. Pensé que tu\nentrenador solo te haría más lenta..."
    },
    {
      "name": "Tamamo Cross",
      "text": "El hándicap te dio una ventaja, y tu energía era\nsalvaje, Creek. ¿Qué diablos pasó?"
    },
    {
      "name": "Super Creek",
      "text": "No lo sé, pero mi pecho no se apretó como siempre\nlo hace, y sentí que mi cuerpo se movía por sí\nsolo...",
      "choice_data_list": [
        "¿Ves? Deberías dejar que <i>yo</i> ayude a <i>ti</i> a veces."
      ]
    },
    {
      "name": "Super Creek",
      "text": "¿Eh?"
    },
    {
      "name": "Monólogo",
      "text": "Le explico que sentirse obligada a cargar con todo\npor su cuenta es la causa de su enfermedad."
    },
    {
      "name": "Monólogo",
      "text": "Cuando le digo que quiero ayudar haciendo que\ndependa un poco más de mí..."
    },
    {
      "name": "Super Creek",
      "text": "Ohhh... Así que por eso..."
    },
    {
      "name": "Super Creek",
      "text": "La idea de que tengo que esforzarme en tu nombre\nes lo que causó todo esto, ¿eh?"
    },
    {
      "name": "Tamamo Cross",
      "text": "Ahora lo entiendo. Supongo que significa que\nestabas demasiado concentrada."
    },
    {
      "name": "Tamamo Cross",
      "text": "Suena exactamente a Creek. Mis respetos por\ndescubrirlo y ayudarla a verlo."
    },
    {
      "name": "Super Creek",
      "text": "Has crecido para ser tan capaz, Entrenador. No\npuedo creer que ni siquiera yo me diera cuenta..."
    },
    {
      "name": "Super Creek",
      "text": "Eres tan buen entrenador, y yo soy tan\nmala\nUmamusume... <i>Snif...</i>",
      "choice_data_list": [
        "Juntos, nos convertiremos en un equipo imparable.",
        "Juntos, nos convertiremos en un equipo imparable."
      ]
    },
    {
      "name": "Super Creek",
      "text": "¡Por supuesto! Ah, cierto... Hay más cosas de las\nque me gustaría hablar contigo, Entrenador."
    },
    {
      "name": "Super Creek",
      "text": "Cuéntame todo lo fuerte que te has vuelto, ¿vale?"
    },
    {
      "name": "Tamamo Cross",
      "text": "Mmm, eso es lo que me gusta ver. ¡Feliz por ti,\nCreek!"
    },
    {
      "name": "Super Creek",
      "text": "Entrenador..."
    },
    {
      "name": "Tamamo Cross",
      "text": "¡Oye! ¿Me estás siquiera escuchando?! ¡No soy solo\nun personaje secundario en tu escena dramática,\n¡lo sabes!"
    },
    {
      "name": "Monólogo",
      "text": "Después, organicé un horario más relajado para el\nverano para que Super Creek pueda relajarse."
    },
    {
      "name": "Monólogo",
      "text": "Varias semanas después..."
    },
    {
      "name": "Super Creek",
      "text": "Jej, nos lo hemos estado pasando genial todos los\ndías. Yo especialmente disfruté darnos de comer en\nel mercado nocturno! ♪"
    },
    {
      "name": "Super Creek",
      "text": "Casi deseo que este campamento de verano nunca\ntermine... Pero esa es la parte perezosa de mí\nhablando.",
      "choice_data_list": [
        "Está bien sentirse así."
      ]
    },
    {
      "name": "Super Creek",
      "text": "Gracias. Me has dado la oportunidad de relajarme\nde verdad."
    },
    {
      "name": "Super Creek",
      "text": "Siento que todo mi cuerpo se está recuperando\nlentamente..."
    },
    {
      "name": "Monólogo",
      "text": "Ella tiene la misma sonrisa que cuando la conocí.\nPor fin he podido hacer algo por ella."
    },
    {
      "name": "Super Creek",
      "text": "Pero nuestro campamento de verano no ha terminado\naún. ¿Cómo quieres pasar el resto?",
      "choice_data_list": [
        "Organicemos un torneo de sumo.",
        "Vamos a una cacería de fantasmas."
      ]
    },
    {
      "name": "Super Creek",
      "text": "¿Un torneo de sumo? ¿Quieres decir en la playa?\n¡Jej, gran idea! ♪"
    },
    {
      "name": "Super Creek",
      "text": "¡Pero no voy a perder! ¡Te apretaré fuerte y te\nharé rodar por el suelo! ¡Jej!"
    },
    {
      "name": "Monólogo",
      "text": "Nos tomamos con calma el resto de nuestro tiempo\njuntos. Super Creek acumula poder mientras se\ndivierte."
    },
    {
      "name": "Super Creek",
      "text": "¿Una cacería de fantasmas? No me importa, pero\ntengo reacciones bastante lentas.",
      "choice_data_list": [
        "¿Qué quieres decir?"
      ]
    },
    {
      "name": "Super Creek",
      "text": "O sea, me toma un tiempo darme cuenta cuando un\nfantasma aparece frente a mí."
    },
    {
      "name": "Super Creek",
      "text": "Por eso, mis gritos siempre llegan unos segundos\ntarde, así que no te rías de mí, ¿vale?"
    },
    {
      "name": "Monólogo",
      "text": "Después, ella reacciona a todos los sustos\nexactamente como describió. Pero cuanto más se\ndivierte, más valiente se vuelve."
    }
  ]
}