{
  "no_wrap": true,
  "text_block_list": [
    {
      "name": "Rice Shower",
      "text": "Uno, dos, uno, dos. Cruzar las<n>piernas aquí..."
    },
    {
      "name": "Rice Shower",
      "text": "¡Hyaaa!"
    },
    {
      "name": "Rice Shower",
      "text": "Ayyy, me equivoqué de nuevo...<n>Tengo que seguir\npracticando...",
      "choice_data_list": [
        "Sudando la gota gorda, ¿eh?",
        "Sudando la gota gorda, ¿eh?"
      ]
    },
    {
      "name": "Rice Shower",
      "text": "¡Gyah! ¿Hermano Mayor?! M-me<n>encontraste..."
    },
    {
      "name": "Rice Shower",
      "text": "¡Gyah! ¿Hermana Mayor?! M-me<n>encontraste..."
    },
    {
      "name": "Rice Shower",
      "text": "Lo siento... Solo pensé que podría<n>practicar un\npoco ya que no había<n>nadie alrededor.",
      "choice_data_list": [
        "¿Por qué practicas sola?"
      ]
    },
    {
      "name": "Rice Shower",
      "text": "Antes, cuando teníamos una lección en<n>clase,\nla... um, la electricidad del<n>estudio se fue."
    },
    {
      "name": "Rice Shower",
      "text": "La lección se canceló... Si yo no<n>hubiera estado\nallí, estoy segura de<n>que eso no habría\npasado..."
    },
    {
      "name": "Rice Shower",
      "text": "Causé un gran lío para todos... Por<n>eso estoy\npracticando sola."
    },
    {
      "name": "Rice Shower",
      "text": "...Deberías irte antes de que también<n>te pase\nalgo malo, Hermano Mayor.",
      "choice_data_list": [
        "¿Te estoy molestando?",
        "¿Te estoy molestando?",
        "¡Estoy listo para lo que sea!"
      ]
    },
    {
      "name": "Rice Shower",
      "text": "...Deberías irte antes de que también<n>te pase\nalgo malo, Hermana Mayor.",
      "choice_data_list": [
        "¿Te estoy molestando?",
        "¿Te estoy molestando?",
        "¡Estoy lista para lo que sea!"
      ]
    },
    {
      "name": "Rice Shower",
      "text": "¡E-eso no es! ¡No me molesta que<n>estés aquí!",
      "choice_data_list": [
        "En ese caso, déjame ayudarte a entrenar."
      ]
    },
    {
      "name": "Rice Shower",
      "text": "¡E-eso no es! ¡No me molesta que<n>estés aquí!",
      "choice_data_list": [
        "En ese caso, déjame ayudarte a entrenar."
      ]
    },
    {
      "name": "Rice Shower",
      "text": "Hermano Mayor..."
    },
    {
      "name": "Rice Shower",
      "text": "Hermana Mayor..."
    },
    {
      "name": "Rice Shower",
      "text": "Gracias."
    },
    {
      "name": "Rice Shower",
      "text": "¿Podrías señalarme las partes del<n>baile donde me\nequivoco?",
      "choice_data_list": [
        "¡Claro! ¡Hagámoslo!"
      ]
    },
    {
      "name": "Rice Shower",
      "text": "¿Podrías señalarme las partes del<n>baile donde me\nequivoco?",
      "choice_data_list": [
        "¡Claro! ¡Hagámoslo!"
      ]
    },
    {
      "name": "Rice Shower",
      "text": "¡Bien!"
    },
    {
      "name": "Monólogo",
      "text": "Rice Shower practica exhaustivamente<n>para\nsuperar sus debilidades al bailar."
    },
    {
      "name": "Rice Shower",
      "text": "¡¿Eh?! ¡N-no, no quiero molestarte!",
      "choice_data_list": [
        "Y yo no quiero verte luchar sola."
      ]
    },
    {
      "name": "Rice Shower",
      "text": "¡¿Eh?! ¡N-no, no quiero molestarte!",
      "choice_data_list": [
        "Y yo no quiero verte luchar sola."
      ]
    },
    {
      "name": "Rice Shower",
      "text": "Hermano Mayor..."
    },
    {
      "name": "Rice Shower",
      "text": "Hermana Mayor..."
    },
    {
      "name": "Rice Shower",
      "text": "¿Entonces... podrías ayudarme con la<n>práctica?",
      "choice_data_list": [
        "¡Definitivamente!"
      ]
    },
    {
      "name": "Rice Shower",
      "text": "¡G-gracias! En realidad hay esta<n>parte difícil..."
    },
    {
      "name": "Monólogo",
      "text": "Continúo ayudando a Rice Shower a<n>practicar\nhasta altas horas de la noche."
    }
  ]
}