{
  "no_wrap": true,
  "text_block_list": [
    {
      "name": "Oguri Cap",
      "text": "¡Mira esto! Hoy me llegó un paquete."
    },
    {
      "name": "Monólogo",
      "text": "Oguri Cap me pasa una bufanda roja del<n>mismo\ncolor que su ropa de carrera característica."
    },
    {
      "name": "Monólogo",
      "text": "Noto que la gente ha escrito mensajes<n>de apoyo\npara ella en el reverso de la<n>bufanda—donde nadie\nmás podría verlos."
    },
    {
      "name": "Monólogo",
      "text": "Recordando lo querida que es, le<n>devuelvo la\nbufanda.",
      "choice_data_list": [
        "¿Es de tu pueblo?"
      ]
    },
    {
      "name": "Oguri Cap",
      "text": "Sí. Todos me escribieron un pequeño<n>mensaje."
    },
    {
      "name": "Oguri Cap",
      "text": "Hay mensajes como, \"Siempre estamos<n>a tu lado\",\n\"Corremos contigo\",<n>y \"Eres la encarnación de\nnuestros<n>sueños\"."
    },
    {
      "name": "Oguri Cap",
      "text": "¿La encarnación de sus sueños? No<n>estoy segura\nde qué quieren decir con eso."
    },
    {
      "name": "Oguri Cap",
      "text": "Sé que verme correr los hace felices...<n>Pero\n¿cómo puedo <i>yo</i> ser su sueño?",
      "choice_data_list": [
        "Están depositando sus esperanzas en ti."
      ]
    },
    {
      "name": "Oguri Cap",
      "text": "...¿Sus esperanzas? ¿En mí?"
    },
    {
      "name": "Monólogo",
      "text": "Le explico a Oguri Cap que ella<n>representa las\naspiraciones, esperanzas y<n>deseos de la gente de\nsu pueblo."
    },
    {
      "name": "Oguri Cap",
      "text": "Suena complicado, pero creo que más<n>o menos lo\nentiendo ahora... Todos me<n>animan y me desean\nlo mejor."
    },
    {
      "name": "Oguri Cap",
      "text": "...Eso me hace sentir muy cálida<n>por dentro—como\nsi no estuviera sola.",
      "choice_data_list": [
        "¿Te sientes presionada?",
        "¿Te sientes presionada?"
      ]
    },
    {
      "name": "Oguri Cap",
      "text": "...Sí, supongo que sí. Pero al mismo<n>tiempo,\nsiento que eso es lo que me<n>impulsa a seguir\nadelante."
    },
    {
      "name": "Oguri Cap",
      "text": "Aunque no estoy segura de que<n>\"presión\" sea la\npalabra correcta... Creo que es<n>más como... ¿ánimo?"
    },
    {
      "name": "Oguri Cap",
      "text": "...Tengo unas ganas abrumadoras de<n>correr.\n¿Vendrás conmigo?",
      "choice_data_list": [
        "¡Por supuesto!"
      ]
    },
    {
      "name": "Oguri Cap",
      "text": "¡Gracias!"
    },
    {
      "name": "Monólogo",
      "text": "Decido quedarme con Oguri Cap hasta<n>que se\nsienta satisfecha."
    },
    {
      "name": "Oguri Cap",
      "text": "<i>Jadeo... jadeo... buf...</i>"
    },
    {
      "name": "Oguri Cap",
      "text": "Al principio era un poco escéptica con<n>este\natuendo. Me preguntaba por qué<n>querías que lo\nusara."
    },
    {
      "name": "Oguri Cap",
      "text": "Pero ahora lo entiendo. La gente lo<n>reconoce\ncomo mi ropa de carrera característica.<n>Por eso\ntodos del pueblo me<n>enviaron esta bufanda."
    },
    {
      "name": "Oguri Cap",
      "text": "Realmente quieren que gane... Y este<n>atuendo\nrepresenta esos sentimientos."
    },
    {
      "name": "Oguri Cap",
      "text": "Yo... siento lo mismo. Realmente<n>quiero ganar.",
      "choice_data_list": [
        "¡Estamos en la misma página!",
        "¡Estamos en la misma página!",
        "¡Vamos a por la victoria—por el bien de todos!"
      ]
    },
    {
      "name": "Oguri Cap",
      "text": "Yo... siento lo mismo. Realmente<n>quiero ganar.",
      "choice_data_list": [
        "¡Estamos en la misma página!",
        "¡Estamos en la misma página!",
        "¡Vamos a por la victoria—por el bien de todos!"
      ]
    },
    {
      "name": "Oguri Cap",
      "text": "Sí, sé que siempre estás a mi lado,<n>apoyándome."
    },
    {
      "name": "Oguri Cap",
      "text": "¡Seguiré corriendo—por los dos!"
    },
    {
      "name": "Oguri Cap",
      "text": "¡Mientras estés conmigo, no puedo perder!"
    },
    {
      "name": "Oguri Cap",
      "text": "Así es. Las esperanzas y sueños de<n>todos\ndescansan sobre mis hombros."
    },
    {
      "name": "Monólogo",
      "text": "Al ver a Oguri Cap llena de\ndeterminación,<n>siento un renovado sentido\nde<n>determinación para la próxima carrera."
    }
  ]
}