{
  "no_wrap": true,
  "text_block_list": [
    {
      "name": "Monólogo",
      "text": "Un día, Mejiro Dober me invita a ir de compras con\nella y Mejiro Ryan."
    },
    {
      "name": "Monólogo",
      "text": "♪♪♪"
    },
    {
      "name": "Mejiro Dober",
      "text": "¿Es esa música? Suena como que viene de por\nallá..."
    },
    {
      "name": "Personal del evento",
      "text": "Desafortunadamente, Taiki Shuttle solo obtuvo\nochenta y nueve puntos. ¡Parece que el gran premio\nde un bistec de primera todavía está en juego!"
    },
    {
      "name": "Taiki Shuttle",
      "text": "¡Oh, no! Y yo que planeaba tener un asado con\ntodos esta noche!"
    },
    {
      "name": "Taiki Shuttle",
      "text": "¡Oh, hola!"
    },
    {
      "name": "Taiki Shuttle",
      "text": "¡Dober, te lo pido! ¡Haz este desafío de karaoke\nconmigo, por favor!"
    },
    {
      "name": "Mejiro Dober",
      "text": "<i>¿¡Yo!?</i>"
    },
    {
      "name": "Personas en el distrito comercial",
      "text": "Oye, parece que habrá una nueva contrincante.\n¡Quedémonos y veamos su actuación también!"
    },
    {
      "name": "Mejiro Dober",
      "text": "Oh, eh... Lo siento, me encantaría ayudar, pero..."
    },
    {
      "name": "Mejiro Ryan",
      "text": "Hm... Espera. Taiki, ¿estaría bien si yo me uniera\nen su lugar?"
    },
    {
      "name": "Mejiro Dober",
      "text": "Ryan..."
    },
    {
      "name": "Mejiro Dober",
      "text": "(Ryan es tan considerada... Cada vez que estoy\nincómoda, ella siempre se ofrece a hacer cosas en\nmi lugar.)"
    },
    {
      "name": "Mejiro Dober",
      "text": "Pero, a este ritmo, terminaré dependiendo de ella\npara siempre..."
    },
    {
      "name": "Personal del evento",
      "text": "¡Todavía aceptamos nuevos retadores, gente! ¿Quién\nquiere aceptar el desafío de karaoke y llevarse a\ncasa ese bistec?!",
      "choice_data_list": [
        "¡Dober, deberías hacerlo!",
        "¿Por qué no aceptar la amable oferta de Ryan?"
      ]
    },
    {
      "name": "Mejiro Dober",
      "text": "...!"
    },
    {
      "name": "Mejiro Ryan",
      "text": "¡¿Qué?! Pero hay demasiada gente aquí. Ella no\ndebería—"
    },
    {
      "name": "Mejiro Dober",
      "text": "No, está bien, Ryan. Quiero intentarlo. Lo\nintentaré."
    },
    {
      "name": "Personal del evento",
      "text": "¡Aplaudan para nuestra siguiente retadora!"
    },
    {
      "name": "Mejiro Dober",
      "text": "...Soy Mejiro Dober. Voy a cantar <i>Here Comes Our\nTime</i>... </i>con mi amiga..."
    },
    {
      "name": "Mejiro Ryan",
      "text": "E-espera, ¿estás segura de esto, Dober?"
    },
    {
      "name": "Monólogo",
      "text": "La máquina de karaoke empieza a tocar música, y\nlos ojos de todos en el distrito comercial se\nvuelven hacia Mejiro Dober."
    },
    {
      "name": "Mejiro Dober",
      "text": "...Ngh."
    },
    {
      "name": "Peatón A",
      "text": "¡Whoa, hey! ¡Es Mejiro Dober! ¡Me encanta su\ncanto!"
    },
    {
      "name": "Peatón B",
      "text": "¿Qué va a cantar? ¿Creen que esté bien si grabo un\nvideo?"
    },
    {
      "name": "Mejiro Dober",
      "text": "...",
      "choice_data_list": [
        "¡Dober! ¡Solo imagina que esto es un concierto!",
        "¡Dober! ¡Solo imagina que esto es un concierto!"
      ]
    },
    {
      "name": "Mejiro Dober",
      "text": "Un concierto..."
    },
    {
      "name": "Mejiro Ryan",
      "text": "¡Exacto! ¡Tú puedes! Tus admiradores siempre\nsienten tu gratitud por su apoyo en tu actuación!"
    },
    {
      "name": "Mejiro Ryan",
      "text": "¡No te preocupes! Sé que serás genial—¡lo\ngarantizo!"
    },
    {
      "name": "Mejiro Dober",
      "text": "...!"
    },
    {
      "name": "Mejiro Dober",
      "text": "Nunca sabes cómo se desenvolverá el destino.\nCuando conoces a un amigo completamente nuevo...",
      "choice_data_list": [
        "(¡Lo logró! ¡Cantó!)"
      ]
    },
    {
      "name": "Mejiro Ryan",
      "text": "¡Buen trabajo, Dober!"
    },
    {
      "name": "Mejiro Ryan",
      "text": "Cada día eres más valiente. Podría aprender un par\nde cosas de ti."
    },
    {
      "name": "Monólogo",
      "text": "Cantar karaoke en medio de la ciudad quizás no sea\ngran cosa para algunos, pero para Mejiro Dober, es\nprueba de cuánto ha crecido."
    },
    {
      "name": "Monólogo",
      "text": "Sin mencionar que logró obtener más de noventa\npuntos y ganó el bistec de primera. Después, los\ncuatro tenemos una fiesta juntos."
    },
    {
      "name": "Mejiro Dober",
      "text": "(¡Esto es tan vergonzoso!)"
    },
    {
      "name": "Mejiro Ryan",
      "text": "Nunca sabes cómo se desenvolverá el destino.\nCuando conoces a un amigo completamente nuevo...",
      "choice_data_list": [
        "¡Se abre una nueva puerta, y ustedes dos se van!"
      ]
    },
    {
      "name": "Mejiro Dober",
      "text": "¿Eh? ¿Ryan? ¿Entrenador?"
    },
    {
      "name": "Mejiro Ryan",
      "text": "Has dado un paso realmente valiente hacia\nadelante, y eso es una hazaña increíble en sí\nmisma."
    },
    {
      "name": "Mejiro Ryan",
      "text": "Pero a veces, puede ser difícil ser valiente solo.\nCuando eso pase, está bien recibir ayuda de otros\nmientras te acostumbras lentamente a exponerte.",
      "choice_data_list": [
        "¿Por qué no cantamos el resto de la canción\njuntas?"
      ]
    },
    {
      "name": "Mejiro Dober",
      "text": "Ustedes dos..."
    },
    {
      "name": "Mejiro Ryan",
      "text": "Mira, ¡la melodía está empezando de nuevo!\nMientras mi corazón late como un tambor quiero\nsaber, ¿qué es este sentimiento?"
    },
    {
      "name": "Mejiro Dober",
      "text": "¿Significa esto que nuestro momento finalmente ha\nllegado?"
    },
    {
      "name": "Mejiro Ryan",
      "text": "Ahora mismo, ese momento parece tan lejano. ♪"
    },
    {
      "name": "Dober y Ryan",
      "text": "Pero nos damos cuenta que de alguna manera,\nnuestros caminos nos llevarán allí algún día!"
    },
    {
      "name": "Monólogo",
      "text": "Aunque no lograron obtener más de noventa puntos,\nganaron algo mucho más valioso de la experiencia\nque un bistec de primera."
    },
    {
      "name": "Mejiro Dober",
      "text": "...¿Eres adivino de pensamientos?",
      "choice_data_list": [
        "Lo siento, quería ofrecer consejo ya que te veías\ntan perdida."
      ]
    },
    {
      "name": "Mejiro Dober",
      "text": "Espera, ¿acabo de decir eso en voz alta?!",
      "choice_data_list": [
        "Lo siento, quería ofrecer consejo ya que te veías\ntan perdida."
      ]
    },
    {
      "name": "Mejiro Dober",
      "text": "...",
      "choice_data_list": [
        "Puedes intentarlo la próxima vez cuando estés más\nmentalmente preparada."
      ]
    },
    {
      "name": "Mejiro Dober",
      "text": "Vale."
    },
    {
      "name": "Mejiro Ryan",
      "text": "¿Hm? ¿Preparada? ¿De qué están hablando?"
    },
    {
      "name": "Mejiro Dober",
      "text": "Oh, no es nada. Solo que no soy muy valiente, eso\nes todo..."
    },
    {
      "name": "Mejiro Ryan",
      "text": "..."
    },
    {
      "name": "Mejiro Ryan",
      "text": "No sé de qué hablas, pero sin duda eres capaz de\nser valiente cuando la situación lo requiera,\nDober."
    },
    {
      "name": "Mejiro Ryan",
      "text": "Así que cuando estés lista, quiero que des todo lo\nque tengas. Yo también te estaré apoyando."
    },
    {
      "name": "Mejiro Dober",
      "text": "Ryan..."
    },
    {
      "name": "Mejiro Dober",
      "text": "Gracias."
    }
  ]
}