{
  "no_wrap": true,
  "text_block_list": [
    {
      "name": "Nice Nature",
      "text": "¡Maldición... Estuve tan cerca!",
      "choice_data_list": [
        "¡Gran trabajo allí!"
      ]
    },
    {
      "name": "Nice Nature",
      "text": "Sí, trabajé duro, ¡pero pude <n>haber dado más!"
    },
    {
      "name": "Nice Nature",
      "text": "Ja... es gracioso."
    },
    {
      "name": "Nice Nature",
      "text": "Normalmente, solo estaría haciendo pucheros,\n<n>diciendo \"Lo sabía\" o algo así."
    },
    {
      "name": "Nice Nature",
      "text": "Pero no ahora. <i>Sé</i> que </i>puedo usar esta<n> experiencia\npara hacerlo mejor en la próxima carrera."
    },
    {
      "name": "Nice Nature",
      "text": "Yo... debo haberme vuelto más fuerte."
    },
    {
      "name": "Mejiro McQueen",
      "text": "¡Impresionante trabajo, Nature!"
    },
    {
      "name": "Nice Nature",
      "text": "¡McQueen! ¡Ryan!"
    },
    {
      "name": "Mejiro McQueen",
      "text": "Aprendí mucho de competir contigo."
    },
    {
      "name": "Mejiro Ryan",
      "text": "Sí, verte darlo todo fue <n>impresionante, ¡Nature!"
    },
    {
      "name": "Mejiro Ryan",
      "text": "¡Corramos juntos de nuevo!"
    },
    {
      "name": "Nice Nature",
      "text": "¡Definitivamente!"
    },
    {
      "name": "Nice Nature",
      "text": "¡Espero con ansias!"
    },
    {
      "name": "Nice Nature",
      "text": "Esos dos realmente saben cómo<n> tomar las cosas con\ncalma. Ya están pensando<n> en el futuro."
    },
    {
      "name": "Nice Nature",
      "text": "Se nota que no se detienen en sus<n> fracasos. En\ncambio, ya están corriendo<n> hacia su próxima\nvictoria."
    },
    {
      "name": "Nice Nature",
      "text": "Teio era igual. Por eso es tan<n> fuerte."
    },
    {
      "name": "Nice Nature",
      "text": "Hasta ahora, siempre me limité, creyendo<n> que no\npodía dar más, sin importar <n>cuánto me esforzara."
    },
    {
      "name": "Nice Nature",
      "text": "Pensaba lo mismo del tercer puesto.<n> Me había dado\npor vencida, pensando que<n> no podía seguir\navanzando..."
    },
    {
      "name": "Nice Nature",
      "text": "Pero eso estaba mal. Si quiero brillar,<n> necesito\ncambiar mi mentalidad."
    },
    {
      "name": "Nice Nature",
      "text": "Necesito apuntar al primer lugar. De esa manera,<n>\nincluso si termino en tercero... sigo avanzando."
    },
    {
      "name": "Monólogo",
      "text": "La duda ya no nubla la visión de Nice <n>Nature.\nIncluso en una carrera más importante,<n> seguirá\ndesafiándose a sí misma y a los demás,<n> sin\ninmutarse."
    },
    {
      "name": "Monólogo",
      "text": "Solo una carrera puede darle aún <n>más confianza y\nprestigio...",
      "choice_data_list": [
        "¿Quieres intentar el Tenno Sho de otoño después?",
        "¿Quieres intentar el Tenno Sho de otoño después?"
      ]
    },
    {
      "name": "Nice Nature",
      "text": "¡El Tenno Sho de otoño!"
    },
    {
      "name": "Nice Nature",
      "text": "¿Yo? ¿En el Tenno Sho? ¿Con su <n>larga historia y\nlegado?"
    },
    {
      "name": "Nice Nature",
      "text": "...No, ¿por qué me estoy poniendo nerviosa otra\nvez?"
    },
    {
      "name": "Nice Nature",
      "text": "No puedo preocuparme por si merezco estar<n> en la\ncarrera. ¡Tengo que creer que soy<n> digna y animarme\na mí misma!"
    },
    {
      "name": "Nice Nature",
      "text": "¡Tomemos ese gran escenario otoñal por<n> asalto!"
    },
    {
      "name": "Monólogo",
      "text": "Y así, decidimos que ella competirá en<n> el Tenno\nSho de otoño, la carrera que <n>determina al mejor\ncorredor de media <n>distancia!"
    }
  ]
}